{
    "configurations": [
        {
            "name": "Win32",
            "includePath": [
                "${workspaceFolder}/**",
                "D:\\C Projects\\Isometric Game + Engine\\external\\SDL3\\SDL3-3.2.28\\x86_64-w64-mingw32\\include",
                "D:\\C Projects\\Isometric Game + Engine\\external\\glad\\include"
            ],
            "defines": [
                "_DEBUG",
                "UNICODE",
                "_UNICODE"
            ],
            "cStandard": "c17",
            "cppStandard": "gnu++17",
            "intelliSenseMode": "linux-gcc-x64"
        }
    ],
    "version": 4
}